pystickynote/__init__.py
pystickynote/__main__.py
pystickynote/config.py
pystickynote/core.py
pystickynote/paths.py
pystickynote/lib/PySimpleGUIQt.py
pystickynote/lib/__init__.py
pystickynote-1.5.1.dist-info/METADATA
pystickynote-1.5.1.dist-info/WHEEL
pystickynote-1.5.1.dist-info/entry_points.txt
pystickynote-1.5.1.dist-info/top_level.txt
pystickynote-1.5.1.dist-info/zip-safe
pystickynote-1.5.1.dist-info/RECORD
